mpilock/__init__.py
mpilock-1.1.0.dist-info/LICENSE
mpilock-1.1.0.dist-info/METADATA
mpilock-1.1.0.dist-info/WHEEL
mpilock-1.1.0.dist-info/top_level.txt
mpilock-1.1.0.dist-info/RECORD
