Metadata-Version: 2.1
Name: mpilock
Version: 1.1.0
Summary: Synchronize read/write access to resources shared between MPI processes.
Home-page: https://github.com/Helveg/zwembad
Author: Robin De Schepper
Author-email: robingilbert.deschepper@unipv.it
License: UNKNOWN
Keywords: mpi pool mpipool zwembad
Platform: UNKNOWN
Classifier: Development Status :: 4 - Beta
Classifier: Intended Audience :: Science/Research
Classifier: Intended Audience :: Developers
Classifier: Topic :: Scientific/Engineering
Classifier: License :: OSI Approved :: BSD License
Classifier: Programming Language :: Python :: 3
Classifier: Programming Language :: Python :: 3.6
Classifier: Programming Language :: Python :: 3.7
Classifier: Programming Language :: Python :: 3.8
Classifier: Programming Language :: Python :: 3.9
Requires-Dist: numpy (>=1.20.0)
Requires-Dist: mpi4py (>=3.0.3)
